py6Nimmt/Card.py
py6Nimmt/Deck.py
py6Nimmt/Player.py
py6Nimmt/Table.py
py6Nimmt/__init__.py
py6Nimmt/buildparser.py
py6Nimmt/py6Nimmt.py
py6Nimmt-0.1.2.dist-info/DESCRIPTION.rst
py6Nimmt-0.1.2.dist-info/METADATA
py6Nimmt-0.1.2.dist-info/RECORD
py6Nimmt-0.1.2.dist-info/WHEEL
py6Nimmt-0.1.2.dist-info/entry_points.txt
py6Nimmt-0.1.2.dist-info/metadata.json
py6Nimmt-0.1.2.dist-info/top_level.txt
tests/__init__.py
tests/context.py
tests/test_main.py
