Metadata-Version: 2.0
Name: py6Nimmt
Version: 0.1.2
Summary: 6 Nimmt! cardgame
Home-page: https://github.com/juanjo78git/py6Nimmt
Author: juanjo78git
Author-email: juanjo78@gmail.com
License: UNKNOWN
Platform: UNKNOWN
Classifier: Programming Language :: Python
Classifier: Development Status :: 4 - Beta
Classifier: License :: OSI Approved :: MIT License
Classifier: Operating System :: OS Independent
Classifier: Programming Language :: Python :: 3.5
Classifier: Topic :: Games/Entertainment :: Board Games
